zepl/__init__.py
zepl/console.py
zepl/user.py
zepl/zepl_cli.py
zepl-1.0.3.dist-info/LICENSE
zepl-1.0.3.dist-info/METADATA
zepl-1.0.3.dist-info/WHEEL
zepl-1.0.3.dist-info/entry_points.txt
zepl-1.0.3.dist-info/top_level.txt
zepl-1.0.3.dist-info/RECORD
